llm_council/__init__.py
llm_council/council.py
llm_council/cli/__init__.py
llm_council/cli/main.py
llm_council/config/__init__.py
llm_council/config/models.py
llm_council/engine/__init__.py
llm_council/engine/degradation.py
llm_council/engine/health.py
llm_council/engine/orchestrator.py
llm_council/logging/__init__.py
llm_council/protocol/__init__.py
llm_council/protocol/types.py
llm_council/providers/__init__.py
llm_council/providers/anthropic.py
llm_council/providers/base.py
llm_council/providers/google.py
llm_council/providers/openai.py
llm_council/providers/openrouter.py
llm_council/providers/registry.py
llm_council/providers/vertex.py
llm_council/providers/cli/__init__.py
llm_council/providers/cli/codex.py
llm_council/providers/cli/gemini.py
llm_council/registry/__init__.py
llm_council/registry/base_agent.py
llm_council/registry/tool_registry.py
llm_council/schemas/__init__.py
llm_council/schemas/architect.json
llm_council/schemas/assessor.json
llm_council/schemas/implementer.json
llm_council/schemas/planner.json
llm_council/schemas/red-team.json
llm_council/schemas/researcher.json
llm_council/schemas/reviewer.json
llm_council/schemas/router.json
llm_council/schemas/shipper.json
llm_council/schemas/test-designer.json
llm_council/storage/__init__.py
llm_council/storage/artifacts.py
llm_council/storage/summarize.py
llm_council/subagents/__init__.py
llm_council/subagents/architect.yaml
llm_council/subagents/assessor.yaml
llm_council/subagents/critic.yaml
llm_council/subagents/drafter.yaml
llm_council/subagents/implementer.yaml
llm_council/subagents/planner.yaml
llm_council/subagents/red-team.yaml
llm_council/subagents/researcher.yaml
llm_council/subagents/reviewer.yaml
llm_council/subagents/router.yaml
llm_council/subagents/shipper.yaml
llm_council/subagents/synthesizer.yaml
llm_council/subagents/test-designer.yaml
llm_council/validation/__init__.py
the_llm_council-0.5.3.dist-info/METADATA
the_llm_council-0.5.3.dist-info/WHEEL
the_llm_council-0.5.3.dist-info/entry_points.txt
the_llm_council-0.5.3.dist-info/licenses/LICENSE
the_llm_council-0.5.3.dist-info/RECORD
