Metadata-Version: 2.4
Name: the-llm-council
Version: 0.5.3
Summary: Multi-LLM Council Framework for adversarial debate, cross-validation, and structured decision-making
Project-URL: Homepage, https://github.com/sherifkozman/the-llm-council
Project-URL: Documentation, https://github.com/sherifkozman/the-llm-council#readme
Project-URL: Repository, https://github.com/sherifkozman/the-llm-council
Project-URL: Issues, https://github.com/sherifkozman/the-llm-council/issues
Author: Sherif Kozman
License-Expression: MIT
License-File: LICENSE
Keywords: adversarial,agents,ai,claude,council,gemini,llm,multi-model,openai
Classifier: Development Status :: 3 - Alpha
Classifier: Intended Audience :: Developers
Classifier: License :: OSI Approved :: MIT License
Classifier: Programming Language :: Python :: 3
Classifier: Programming Language :: Python :: 3.10
Classifier: Programming Language :: Python :: 3.11
Classifier: Programming Language :: Python :: 3.12
Classifier: Topic :: Scientific/Engineering :: Artificial Intelligence
Requires-Python: >=3.10
Requires-Dist: aiosqlite>=0.19
Requires-Dist: httpx>=0.25
Requires-Dist: jsonschema>=4.0
Requires-Dist: pydantic>=2.0
Requires-Dist: pyyaml>=6.0
Requires-Dist: rich>=13.0
Requires-Dist: typer>=0.9
Provides-Extra: all
Requires-Dist: anthropic>=0.18; extra == 'all'
Requires-Dist: anthropic[vertex]>=0.18; extra == 'all'
Requires-Dist: google-auth>=2.0; extra == 'all'
Requires-Dist: google-genai>=1.0; extra == 'all'
Requires-Dist: openai>=1.0; extra == 'all'
Provides-Extra: anthropic
Requires-Dist: anthropic>=0.18; extra == 'anthropic'
Provides-Extra: dev
Requires-Dist: mypy>=1.0; extra == 'dev'
Requires-Dist: pytest-asyncio>=0.21; extra == 'dev'
Requires-Dist: pytest-cov>=4.0; extra == 'dev'
Requires-Dist: pytest>=7.0; extra == 'dev'
Requires-Dist: ruff>=0.1; extra == 'dev'
Requires-Dist: types-jsonschema>=4.0; extra == 'dev'
Requires-Dist: types-pyyaml>=6.0; extra == 'dev'
Provides-Extra: google
Requires-Dist: google-genai>=1.0; extra == 'google'
Provides-Extra: openai
Requires-Dist: openai>=1.0; extra == 'openai'
Provides-Extra: vertex
Requires-Dist: anthropic[vertex]>=0.18; extra == 'vertex'
Requires-Dist: google-auth>=2.0; extra == 'vertex'
Requires-Dist: google-genai>=1.0; extra == 'vertex'
